commit_gpt/__init__.py
commit_gpt/cli.py
commit_gpt/formatters.py
commit_gpt/gitio.py
commit_gpt/llm.py
commit_gpt/prompts.py
commit_gpt/redact.py
commit_gpt/risk.py
smart_commit_gpt-1.0.2.dist-info/METADATA
smart_commit_gpt-1.0.2.dist-info/WHEEL
smart_commit_gpt-1.0.2.dist-info/entry_points.txt
smart_commit_gpt-1.0.2.dist-info/licenses/LICENSE
smart_commit_gpt-1.0.2.dist-info/RECORD
